LICENSE
README.md
setup.py
JMTrucoCmd/__init__.py
JMTrucoCmd.egg-info/PKG-INFO
JMTrucoCmd.egg-info/SOURCES.txt
JMTrucoCmd.egg-info/dependency_links.txt
JMTrucoCmd.egg-info/requires.txt
JMTrucoCmd.egg-info/top_level.txt
JMTrucoCmd/functions/bots.py
JMTrucoCmd/functions/deck.py
JMTrucoCmd/functions/sistem.py
JMTrucoCmd/models/bot.py
JMTrucoCmd/models/card.py
JMTrucoCmd/models/game.py
JMTrucoCmd/models/stats.py
JMTrucoCmd/models/type_card.py
JMTrucoCmd/schemas/bot.py
JMTrucoCmd/schemas/card.py
JMTrucoCmd/schemas/deck.py
JMTrucoCmd/schemas/stats.py
JMTrucoCmd/schemas/type_card.py
JmTrucoCmd/data/bots.py